shadowwatch/__init__.py
shadowwatch/main.py
shadowwatch/core/__init__.py
shadowwatch/core/fingerprint.py
shadowwatch/core/pruner.py
shadowwatch/core/scorer.py
shadowwatch/core/tracker.py
shadowwatch/core/trust_score.py
shadowwatch/integrations/__init__.py
shadowwatch/integrations/fastapi.py
shadowwatch/models/__init__.py
shadowwatch/models/activity.py
shadowwatch/models/interest.py
shadowwatch/models/library.py
shadowwatch/utils/__init__.py
shadowwatch/utils/cache.py
shadowwatch/utils/license.py
shadowwatch/utils/validators.py
shadowwatch-0.3.0.dist-info/licenses/LICENSE
shadowwatch-0.3.0.dist-info/METADATA
shadowwatch-0.3.0.dist-info/WHEEL
shadowwatch-0.3.0.dist-info/top_level.txt
shadowwatch-0.3.0.dist-info/RECORD
