Metadata-Version: 2.4
Name: shadowwatch
Version: 0.3.0
Summary: Behavioral intelligence for your application
Home-page: https://github.com/Tanishq1030/Shadow_Watch
Author: Tanishq Dasari
Author-email: Tanishq Dasari <tanishqdasari2004@gmail.com>
License: MIT
Project-URL: Homepage, https://github.com/Tanishq1030/Shadow_Watch
Project-URL: Documentation, https://github.com/Tanishq1030/Shadow_Watch#readme
Project-URL: Repository, https://github.com/Tanishq1030/Shadow_Watch
Project-URL: Bug Reports, https://github.com/Tanishq1030/Shadow_Watch/issues
Keywords: behavioral,biometrics,fraud-detection,security,personalization
Classifier: Development Status :: 3 - Alpha
Classifier: Intended Audience :: Developers
Classifier: Topic :: Security
Classifier: License :: OSI Approved :: MIT License
Classifier: Programming Language :: Python :: 3
Requires-Python: >=3.9
License-File: LICENSE
Requires-Dist: sqlalchemy>=2.0.0
Requires-Dist: httpx>=0.25.0
Provides-Extra: dev
Requires-Dist: pytest>=7.0.0; extra == "dev"
Requires-Dist: pytest-asyncio>=0.21.0; extra == "dev"
Requires-Dist: black>=23.0.0; extra == "dev"
Requires-Dist: flake8>=6.0.0; extra == "dev"
Provides-Extra: redis
Requires-Dist: redis>=5.0.0; extra == "redis"
Dynamic: author
Dynamic: home-page
Dynamic: license-file
Dynamic: requires-python
